openapi_cli/__init__.py
openapi_cli/_client.py
openapi_cli/cli.py
openapi_cli/config.py
openapi_cli/helpers.py
openapi_cli/interfaces/__init__.py
openapi_cli/interfaces/action.py
openapi_cli/interfaces/client.py
openapi_cli/interfaces/completions.py
openapi_cli/interfaces/configure.py
openapi_cli/interfaces/main.py
openapi_cli/interfaces/misc.py
openapi_cli/patcher.py
openapi_cli/separator.py
openapi_cli/symbols.py
openapi_cli/templates/.gitignore.jinja
openapi_cli/templates/README.md.jinja
openapi_cli/templates/api_init.py.jinja
openapi_cli/templates/client.py.jinja
openapi_cli/templates/endpoint_init.py.jinja
openapi_cli/templates/endpoint_macros.py.jinja
openapi_cli/templates/endpoint_module.py.jinja
openapi_cli/templates/errors.py.jinja
openapi_cli/templates/helpers.jinja
openapi_cli/templates/int_enum.py.jinja
openapi_cli/templates/models_init.py.jinja
openapi_cli/templates/package_init.py.jinja
openapi_cli/templates/property_templates/any_property.py.jinja
openapi_cli/templates/property_templates/boolean_property.py.jinja
openapi_cli/templates/property_templates/const_property.py.jinja
openapi_cli/templates/property_templates/date_property.py.jinja
openapi_cli/templates/property_templates/datetime_property.py.jinja
openapi_cli/templates/property_templates/enum_property.py.jinja
openapi_cli/templates/property_templates/file_property.py.jinja
openapi_cli/templates/property_templates/float_property.py.jinja
openapi_cli/templates/property_templates/helpers.jinja
openapi_cli/templates/property_templates/int_property.py.jinja
openapi_cli/templates/property_templates/list_property.py.jinja
openapi_cli/templates/property_templates/model_property.py.jinja
openapi_cli/templates/property_templates/property_macros.py.jinja
openapi_cli/templates/property_templates/union_property.py.jinja
openapi_cli/templates/pyproject.toml.jinja
openapi_cli/templates/pyproject_ruff.toml.jinja
openapi_cli/templates/setup.py.jinja
openapi_cli/templates/str_enum.py.jinja
openapi_cli-0.2.1.14.dist-info/LICENSE
openapi_cli-0.2.1.14.dist-info/METADATA
openapi_cli-0.2.1.14.dist-info/WHEEL
openapi_cli-0.2.1.14.dist-info/entry_points.txt
openapi_cli-0.2.1.14.dist-info/RECORD
