Metadata-Version: 2.1
Name: openapi-cli
Version: 0.2.1.14
Summary: Use OpenAPI schema to generate command line client
Author: Yury Sokov (Yurzs)
Author-email: me@yurzs.dev
Requires-Python: >=3.11,<4
Classifier: Programming Language :: Python :: 3
Classifier: Programming Language :: Python :: 3.11
Classifier: Programming Language :: Python :: 3.12
Classifier: Programming Language :: Python :: 3.13
Provides-Extra: full
Requires-Dist: cattrs (>=23.2.3,<24.0.0) ; extra == "full"
Requires-Dist: click (>=8.1) ; extra == "full"
Requires-Dist: click-didyoumean (>=0.3.1,<0.4.0) ; extra == "full"
Requires-Dist: httpx (>=0.27,<1) ; extra == "full"
Requires-Dist: openapi-python-client (==0.21) ; extra == "full"
Requires-Dist: plumbum (>=1.8.3,<2.0.0) ; extra == "full"
Requires-Dist: pydantic (>=2.8.2,<3.0.0) ; extra == "full"
Requires-Dist: ruff (>=0.4) ; extra == "full"
